content_editor/__init__.py
content_editor/admin.py
content_editor/contents.py
content_editor/models.py
content_editor/locale/ca/LC_MESSAGES/django.mo
content_editor/locale/ca/LC_MESSAGES/django.po
content_editor/locale/cs/LC_MESSAGES/django.mo
content_editor/locale/cs/LC_MESSAGES/django.po
content_editor/locale/de/LC_MESSAGES/django.mo
content_editor/locale/de/LC_MESSAGES/django.po
content_editor/locale/es/LC_MESSAGES/django.mo
content_editor/locale/es/LC_MESSAGES/django.po
content_editor/locale/fr/LC_MESSAGES/django.mo
content_editor/locale/fr/LC_MESSAGES/django.po
content_editor/locale/hr/LC_MESSAGES/django.mo
content_editor/locale/hr/LC_MESSAGES/django.po
content_editor/locale/it/LC_MESSAGES/django.mo
content_editor/locale/it/LC_MESSAGES/django.po
content_editor/locale/nb/LC_MESSAGES/django.mo
content_editor/locale/nb/LC_MESSAGES/django.po
content_editor/locale/nl/LC_MESSAGES/django.mo
content_editor/locale/nl/LC_MESSAGES/django.po
content_editor/locale/pl/LC_MESSAGES/django.mo
content_editor/locale/pl/LC_MESSAGES/django.po
content_editor/locale/pt/LC_MESSAGES/django.mo
content_editor/locale/pt/LC_MESSAGES/django.po
content_editor/locale/pt/LC_MESSAGES/djangojs.mo
content_editor/locale/pt/LC_MESSAGES/djangojs.po
content_editor/locale/pt_BR/LC_MESSAGES/django.mo
content_editor/locale/pt_BR/LC_MESSAGES/django.po
content_editor/locale/ro/LC_MESSAGES/django.mo
content_editor/locale/ro/LC_MESSAGES/django.po
content_editor/locale/ru/LC_MESSAGES/django.mo
content_editor/locale/ru/LC_MESSAGES/django.po
content_editor/locale/tr/LC_MESSAGES/django.mo
content_editor/locale/tr/LC_MESSAGES/django.po
content_editor/locale/zh_CN/LC_MESSAGES/django.mo
content_editor/locale/zh_CN/LC_MESSAGES/django.po
content_editor/static/content_editor/content_editor.css
content_editor/static/content_editor/content_editor.js
content_editor/static/content_editor/django_admin_fixes.css
content_editor/static/content_editor/material-icons.css
django_content_editor-8.0.3.dist-info/METADATA
django_content_editor-8.0.3.dist-info/WHEEL
django_content_editor-8.0.3.dist-info/licenses/AUTHORS
django_content_editor-8.0.3.dist-info/licenses/LICENSE
django_content_editor-8.0.3.dist-info/RECORD
